pycite/__init__.py
pycite/__main__.py
pycite/helpers.py
pycite/jstor.py
pycite/ncbi.py
pycite/pubmed.py
pycite/pycite.py
pycite/sciencedirect.py
pycite/version.py
pycite-0.1.3.dist-info/LICENSE
pycite-0.1.3.dist-info/METADATA
pycite-0.1.3.dist-info/WHEEL
pycite-0.1.3.dist-info/top_level.txt
pycite-0.1.3.dist-info/RECORD
