Metadata-Version: 2.1
Name: pycite
Version: 0.1.3
Summary: Python Citations Generator
Home-page: http://www.github.com/Nelson-Gon/pycite
Author: Nelson Gonzabato
Author-email: gonzabato@hotmail.com
License: MIT
Download-URL: https://github.com/Nelson-Gon/pycite/archive/refs/tags/v0.1.3.zip
Keywords: web html academics citation science
Platform: UNKNOWN
Requires-Python: >=3.6
Requires-Dist: bs4
